{
  "@context": "https://schema.org",
  "@type": "Course",
  "name": "Description generation course",
  "description": "Introductory course to containers and containerization with Docker. Introduces containerization with Docker and relevant concepts such as image and volume. After completion, students are able to run containerized applications, containerize applications, utilize volumes to store data persistently outside containers, use port mapping to enable access via TCP to containerized applications, and share their own containers publicly. No hard prerequisites; Linux operating systems and web development experience are useful.",
  "courseCode": "TEST001",
  "coursePrerequisites": [
    "No hard prerequisites",
    "Linux operating systems and web development experience are useful"
  ],
  "audience": ["students"],
  "numberOfCredits": 0,
  "publisher": {
    "@type": "Organization",
    "name": "University of Helsinki",
    "sameAs": "https://www.helsinki.fi/"
  },
  "inLanguage": { "@type": "Language", "alternateName": "en" },
  "provider": {
    "@type": "Organization",
    "name": "University of Helsinki",
    "sameAs": "https://www.helsinki.fi/"
  },
  "hasCourseInstance": [
    {
      "@type": "CourseInstance",
      "name": null,
      "courseMode": ["MOOC", "online"],
      "startDate": null,
      "endDate": null
    }
  ]
}
