{
  "db_name": "PostgreSQL",
  "query": "\nSELECT id\nFROM chatbot_conversations\nWHERE id = $1\n  AND user_id = $2\n  AND chatbot_configuration_id = $3\n  AND deleted_at IS NULL\n        ",
  "describe": {
    "columns": [
      {
        "ordinal": 0,
        "name": "id",
        "type_info": "Uuid",
        "origin": {
          "Table": {
            "table": "chatbot_conversations",
            "name": "id"
          }
        }
      }
    ],
    "parameters": {
      "Left": [
        "Uuid",
        "Uuid",
        "Uuid"
      ]
    },
    "nullable": [
      false
    ]
  },
  "hash": "888c164504991be2b76da4ffda0362df661bcb0664b23c193022d1f33f08ff82"
}
