{
  "db_name": "PostgreSQL",
  "query": "\nSELECT user_id,\n  created_at,\n  updated_at,\n  email,\n  first_name,\n  last_name,\n  search_helper\nFROM (\n    SELECT *,\n      LOWER($1) <<->search_helper AS dist\n    FROM user_details\n    ORDER BY dist, LENGTH(search_helper)\n    LIMIT 100\n  ) search\nWHERE dist < 0.7;\n",
  "describe": {
    "columns": [
      {
        "ordinal": 0,
        "name": "user_id",
        "type_info": "Uuid"
      },
      {
        "ordinal": 1,
        "name": "created_at",
        "type_info": "Timestamptz"
      },
      {
        "ordinal": 2,
        "name": "updated_at",
        "type_info": "Timestamptz"
      },
      {
        "ordinal": 3,
        "name": "email",
        "type_info": "Varchar"
      },
      {
        "ordinal": 4,
        "name": "first_name",
        "type_info": "Varchar"
      },
      {
        "ordinal": 5,
        "name": "last_name",
        "type_info": "Varchar"
      },
      {
        "ordinal": 6,
        "name": "search_helper",
        "type_info": "Text"
      }
    ],
    "parameters": {
      "Left": [
        "Text"
      ]
    },
    "nullable": [
      false,
      false,
      false,
      false,
      true,
      true,
      true
    ]
  },
  "hash": "c0dd6d2b9663471b98655ac0294c034bf6cd886c4da906b01de700bddd7aaf7f"
}
