{
  "db_name": "PostgreSQL",
  "query": "\nSELECT *\nFROM user_passwords\nWHERE user_id = $1\n    ",
  "describe": {
    "columns": [
      {
        "ordinal": 0,
        "name": "user_id",
        "type_info": "Uuid"
      },
      {
        "ordinal": 1,
        "name": "password_hash",
        "type_info": "Text"
      },
      {
        "ordinal": 2,
        "name": "created_at",
        "type_info": "Timestamptz"
      },
      {
        "ordinal": 3,
        "name": "updated_at",
        "type_info": "Timestamptz"
      },
      {
        "ordinal": 4,
        "name": "deleted_at",
        "type_info": "Timestamptz"
      }
    ],
    "parameters": {
      "Left": ["Uuid"]
    },
    "nullable": [false, false, false, false, true]
  },
  "hash": "eba52745ce1e02568d451010ede1ad771175e2d67e43bcf3af4306f1d80bc5cf"
}
