{
  "db_name": "PostgreSQL",
  "query": "\nUPDATE code_giveaway_codes\nSET deleted_at = now()\nWHERE id = $1\nAND deleted_at IS NULL\nRETURNING *\n        ",
  "describe": {
    "columns": [
      {
        "ordinal": 0,
        "name": "id",
        "type_info": "Uuid",
        "origin": {
          "Table": {
            "table": "code_giveaway_codes",
            "name": "id"
          }
        }
      },
      {
        "ordinal": 1,
        "name": "created_at",
        "type_info": "Timestamptz",
        "origin": {
          "Table": {
            "table": "code_giveaway_codes",
            "name": "created_at"
          }
        }
      },
      {
        "ordinal": 2,
        "name": "updated_at",
        "type_info": "Timestamptz",
        "origin": {
          "Table": {
            "table": "code_giveaway_codes",
            "name": "updated_at"
          }
        }
      },
      {
        "ordinal": 3,
        "name": "deleted_at",
        "type_info": "Timestamptz",
        "origin": {
          "Table": {
            "table": "code_giveaway_codes",
            "name": "deleted_at"
          }
        }
      },
      {
        "ordinal": 4,
        "name": "code_giveaway_id",
        "type_info": "Uuid",
        "origin": {
          "Table": {
            "table": "code_giveaway_codes",
            "name": "code_giveaway_id"
          }
        }
      },
      {
        "ordinal": 5,
        "name": "code_given_to_user_id",
        "type_info": "Uuid",
        "origin": {
          "Table": {
            "table": "code_giveaway_codes",
            "name": "code_given_to_user_id"
          }
        }
      },
      {
        "ordinal": 6,
        "name": "added_by_user_id",
        "type_info": "Uuid",
        "origin": {
          "Table": {
            "table": "code_giveaway_codes",
            "name": "added_by_user_id"
          }
        }
      },
      {
        "ordinal": 7,
        "name": "code",
        "type_info": "Varchar",
        "origin": {
          "Table": {
            "table": "code_giveaway_codes",
            "name": "code"
          }
        }
      }
    ],
    "parameters": {
      "Left": [
        "Uuid"
      ]
    },
    "nullable": [
      false,
      false,
      false,
      true,
      false,
      true,
      false,
      false
    ]
  },
  "hash": "87b805308a1ebcfe600417672e255884b2bc546e173ce0deca6b7510b83016fc"
}
