{
  "db_name": "PostgreSQL",
  "query": "\nINSERT INTO roles (\n    id,\n    user_id,\n    organization_id,\n    course_id,\n    role\n  )\nSELECT uuid_generate_v5($2, id::text),\n  user_id,\n  organization_id,\n  $2,\n  role\nFROM roles\nWHERE (course_id = $1)\nAND NOT (user_id = $3)\nAND deleted_at IS NULL;\n    ",
  "describe": {
    "columns": [],
    "parameters": {
      "Left": [
        "Uuid",
        "Uuid",
        "Uuid"
      ]
    },
    "nullable": []
  },
  "hash": "4dfad46c56a2f729b23734eeb99f9cc249b333ee5a0ac7420c3a52cbe941540e"
}
