{
  "db_name": "PostgreSQL",
  "query": "\n            INSERT INTO oauth_clients (\n                client_id,\n                client_secret,\n                pepper_id,\n                redirect_uris,\n                grant_types,\n                scope,\n                origin,\n                bearer_allowed\n            )\n            VALUES ($1, $2, $3, $4, $5, $6, $7, $8)\n            RETURNING id\n            ",
  "describe": {
    "columns": [
      {
        "ordinal": 0,
        "name": "id",
        "type_info": "Uuid"
      }
    ],
    "parameters": {
      "Left": ["Text", "Bytea", "Int2", "TextArray", "TextArray", "Text", "Text", "Bool"]
    },
    "nullable": [false]
  },
  "hash": "812c25373ea65fbb5d9ac51c63455913b5a196cbff11dbc19f5ab67830dd3c81"
}
