{
  "db_name": "PostgreSQL",
  "query": "\nUPDATE chatbot_configurations AS cc\nSET\n    enabled_to_students = $1,\n    chatbot_name = $2,\n    prompt = $3,\n    initial_message = $4,\n    weekly_tokens_per_user = $5,\n    daily_tokens_per_user = $6,\n    temperature = $7,\n    top_p = $8,\n    frequency_penalty = $9,\n    presence_penalty = $10,\n    response_max_tokens = $11,\n    use_azure_search = $12,\n    maintain_azure_search_index = $12,\n    hide_citations = $13,\n    use_semantic_reranking = $14,\n    default_chatbot = $15\nWHERE cc.id = $16\nRETURNING *",
  "describe": {
    "columns": [
      {
        "ordinal": 0,
        "name": "id",
        "type_info": "Uuid"
      },
      {
        "ordinal": 1,
        "name": "created_at",
        "type_info": "Timestamptz"
      },
      {
        "ordinal": 2,
        "name": "updated_at",
        "type_info": "Timestamptz"
      },
      {
        "ordinal": 3,
        "name": "deleted_at",
        "type_info": "Timestamptz"
      },
      {
        "ordinal": 4,
        "name": "course_id",
        "type_info": "Uuid"
      },
      {
        "ordinal": 5,
        "name": "enabled_to_students",
        "type_info": "Bool"
      },
      {
        "ordinal": 6,
        "name": "chatbot_name",
        "type_info": "Varchar"
      },
      {
        "ordinal": 7,
        "name": "prompt",
        "type_info": "Varchar"
      },
      {
        "ordinal": 8,
        "name": "initial_message",
        "type_info": "Varchar"
      },
      {
        "ordinal": 9,
        "name": "weekly_tokens_per_user",
        "type_info": "Int4"
      },
      {
        "ordinal": 10,
        "name": "daily_tokens_per_user",
        "type_info": "Int4"
      },
      {
        "ordinal": 11,
        "name": "temperature",
        "type_info": "Float4"
      },
      {
        "ordinal": 12,
        "name": "top_p",
        "type_info": "Float4"
      },
      {
        "ordinal": 13,
        "name": "frequency_penalty",
        "type_info": "Float4"
      },
      {
        "ordinal": 14,
        "name": "presence_penalty",
        "type_info": "Float4"
      },
      {
        "ordinal": 15,
        "name": "response_max_tokens",
        "type_info": "Int4"
      },
      {
        "ordinal": 16,
        "name": "use_azure_search",
        "type_info": "Bool"
      },
      {
        "ordinal": 17,
        "name": "maintain_azure_search_index",
        "type_info": "Bool"
      },
      {
        "ordinal": 18,
        "name": "use_semantic_reranking",
        "type_info": "Bool"
      },
      {
        "ordinal": 19,
        "name": "hide_citations",
        "type_info": "Bool"
      },
      {
        "ordinal": 20,
        "name": "default_chatbot",
        "type_info": "Bool"
      }
    ],
    "parameters": {
      "Left": [
        "Bool",
        "Varchar",
        "Varchar",
        "Varchar",
        "Int4",
        "Int4",
        "Float4",
        "Float4",
        "Float4",
        "Float4",
        "Int4",
        "Bool",
        "Bool",
        "Bool",
        "Bool",
        "Uuid"
      ]
    },
    "nullable": [
      false,
      false,
      false,
      true,
      false,
      false,
      false,
      false,
      false,
      false,
      false,
      false,
      false,
      false,
      false,
      false,
      false,
      false,
      false,
      false,
      false
    ]
  },
  "hash": "d2531d80fd44f397ae919987d6a8393dcd36b41901522fbf79693b3a270355ba"
}
